{
  "id": "level_storyteller_01",
  "title": "3 présidents destitués",
  "cells": 6,
  "cardsCaracter": [
    { "id": "macron", "label": "Macron", "type": "character" },
    { "id": "melenchon", "label": "Mélenchon", "type": "character" },
    { "id": "lepen", "label": "Le Pen", "type": "character" }
  ],
  "cardsPlace": [
    {
      "id": "eviction",
      "label": "Eviction",
      "type": "location",
      "slots": {
        "positions": ["left", "right"],
        "maxCharacters": 2,
        "rules": "Le personnage à gauche doit être plus populaire que celui à droite pour réussir la destitution"
      }
    },
    {
      "id": "popularite",
      "label": "Popularité",
      "type": "location",
      "slots": {
        "maxCharacters": 1,
        "rules": "Détermine quel personnage peut destituer le président actuel"
      }
    }
  ],
  "sequence_destitution": [
    {
      "destiteur": "melenchon",
      "destitué": "macron",
      "resultat": "Macron est destitué, Mélenchon devient président",
      "popularite_necessaire": "Mélenchon > Macron"
    },
    {
      "destiteur": "lepen",
      "destitué": "melenchon",
      "resultat": "Mélenchon est destitué, Le Pen devient présidente",
      "popularite_necessaire": "Le Pen > Mélenchon"
    },
    {
      "destiteur": "macron",
      "destitué": "lepen",
      "resultat": "Le Pen est destituée, Macron devient président",
      "popularite_necessaire": "Macron > Le Pen"
    }
  ]
}
