{
  "id": "level_storyteller_0create",
  "shortTitle": "Créez votre niveau",
  "title": "Créez votre LV, placez les cases et appuyez sur PROPOSER",
  "cells": 6,
  "cardsCaracter": [
    { "id": "macron", "label": "Macron", "type": "character" },
    { "id": "melenchon", "label": "Mélenchon", "type": "character" },
    { "id": "lepen", "label": "Le Pen", "type": "character" },
    { "id": "peuple", "label": "Peuple", "type": "character" },
    { "id": "lobby", "label": "Lobby", "type": "character" },
    { "id": "ministre", "label": "ministre", "type": "character" },
    { "id": "kadafi", "label": "Kadafi", "type": "character" },
    { "id": "sarko", "label": "Sarko", "type": "character" },
    { "id": "mediapart", "label": "Mediapart", "type": "character" },
    { "id": "fillon", "label": "Fillon", "type": "character" },
    { "id": "entreprise", "label": "Entreprise Polluante", "type": "character" }
  ],
  "cardsPlace": [
    {
      "id": "enquete",
      "label": "Enquete",
      "type": "location",
      "slots": {
        "maxCharacters": 2,
        "positions": ["left", "right"],
        "rules": "Lance une enquête pour trouver des preuves contre un personnage"
      }
    },
    {
      "id": "tv",
      "label": "Plateau TV",
      "type": "location",
      "slots": {
        "maxCharacters": 1,
        "rules": "Le Plateau TV permet de confronter deux personnages"
      }
    },
    {
      "id": "tribunal",
      "label": "Tribunal",
      "type": "location",
      "slots": {
        "maxCharacters": 1,
        "rules": "Au tribunal, un personnage peut être condamné"
      }
    },
    {
      "id": "eviction",
      "label": "Éviction",
      "type": "location",
      "slots": {
        "maxCharacters": 2,
        "positions": ["left", "right"],
        "rules": "Un personnage peut être évincé du pouvoir"
      }
    },
    {
      "id": "manifestation",
      "label": "Manifestation",
      "type": "location",
      "slots": { "maxCharacters": 1, "rules": "Peuple peut s’opposer à un personnage" }
    }
  ],
  "victoryStates": []
}
